pddlpy/__init__.py
pddlpy/pddl.py
pddlpy/pddlLexer.py
pddlpy/pddlListener.py
pddlpy/pddlParser.py
planning_graph/__init__.py
planning_graph/pddl_adapter.py
planning_graph/planning_graph.py
planning_graph/planning_graph_planner.py
tests/__init__.py
tests/test_pddl_adapter.py
tests/test_planning_graph.py
tests/test_planning_graph_planner.py
planning_graph-0.0.1.dist-info/LICENSE
planning_graph-0.0.1.dist-info/METADATA
planning_graph-0.0.1.dist-info/WHEEL
planning_graph-0.0.1.dist-info/top_level.txt
planning_graph-0.0.1.dist-info/RECORD
