Metadata-Version: 2.1
Name: planning-graph
Version: 0.0.1
Summary: Planning Graph for AI Planning
Home-page: https://github.com/debbynirwan/planning_graph
Author: Debby Nirwan
Author-email: debby_nirwan@yahoo.com
License: Apache License, Version 2.0
Platform: Python 3
Classifier: Programming Language :: Python :: 3
Classifier: License :: OSI Approved :: Apache Software License
Classifier: Operating System :: OS Independent
Requires-Python: >=3.6
